MANIFEST.in
README.md
setup.cfg
setup.py
ostsa/__init__.py
ostsa.egg-info/PKG-INFO
ostsa.egg-info/SOURCES.txt
ostsa.egg-info/dependency_links.txt
ostsa.egg-info/requires.txt
ostsa.egg-info/top_level.txt
ostsa/automation/__init__.py
ostsa/automation/extract_batch.py
ostsa/automation/hyperparameter_grid_search.py
ostsa/automation/time_extraction.py
ostsa/classification/BaggedClassifier.py
ostsa/classification/Classifier.py
ostsa/classification/__init__.py
ostsa/exe/__init__.py
ostsa/exe/classifier.clsf
ostsa/exe/feature_matrix.csv
ostsa/exe/automation/__init__.py
ostsa/exe/automation/extract_kaggle_batch.py
ostsa/exe/automation/get_kaggle_sample_names.py
ostsa/exe/classification/ExeClassifier.py
ostsa/exe/classification/LogisticRegressionClassifier.py
ostsa/exe/classification/XGBClassifier.py
ostsa/exe/classification/__init__.py
ostsa/exe/storage/ExeKaggleSample.py
ostsa/exe/storage/ExeRawSample.py
ostsa/exe/storage/ExeSample.py
ostsa/exe/storage/ExeSampleBase.py
ostsa/exe/storage/__init__.py
ostsa/parsing/Parser.py
ostsa/parsing/__init__.py
ostsa/parsing/memoize.py
ostsa/storage/Sample.py
ostsa/storage/SampleDao.py
ostsa/storage/__init__.py
scripts/__init__.py
scripts/Exe/__init__.py
scripts/Exe/create_classifier.py
scripts/Exe/create_submission.py
scripts/Exe/evaluate_classifier.py
scripts/Exe/extract_kaggle_samples.py
scripts/Exe/save_feature_matrix.py
scripts/Exe/test_hyperparameters.py
tests/TestCase.py
tests/__init__.py
tests/test_search.py