Metadata-Version: 1.1
Name: ostsa
Version: 0.1.8.1
Summary: A library for classifying malware files. This library also contains various utilities for extending/building your own specialized machine learning classifiers.
Home-page: https://github.com/psb-seclab/malware_classifier
Author: Caleb Rush, Austin Julio, Andy Zheng
Author-email: cir5274@psu.edu
License: UNKNOWN
Download-URL: https://github.com/psb-seclab/malware_classifier/archive/0.1.1.tar.gz
Keywords: machine learning,malware,pe,exe,dll,classifier,security,analysis
Platform: UNKNOWN
